image_crop_component/__init__.py
image_crop_component/frontend/build/asset-manifest.json
image_crop_component/frontend/build/bootstrap.min.css
image_crop_component/frontend/build/index.html
image_crop_component/frontend/build/static/css/main.24eb18d7.chunk.css
image_crop_component/frontend/build/static/css/main.24eb18d7.chunk.css.map
image_crop_component/frontend/build/static/js/2.8f14be39.chunk.js
image_crop_component/frontend/build/static/js/2.8f14be39.chunk.js.LICENSE.txt
image_crop_component/frontend/build/static/js/2.8f14be39.chunk.js.map
image_crop_component/frontend/build/static/js/main.03ec7517.chunk.js
image_crop_component/frontend/build/static/js/main.03ec7517.chunk.js.map
image_crop_component/frontend/build/static/js/runtime-main.c6da4008.js
image_crop_component/frontend/build/static/js/runtime-main.c6da4008.js.map
streamlit_image_crop_component-0.0.2.dist-info/LICENSE
streamlit_image_crop_component-0.0.2.dist-info/METADATA
streamlit_image_crop_component-0.0.2.dist-info/WHEEL
streamlit_image_crop_component-0.0.2.dist-info/top_level.txt
streamlit_image_crop_component-0.0.2.dist-info/RECORD
